<?xml version="1.0" ?>
<session sessionId="2992" date="2009-09-01" time="12:00:58" experimentType="emotion elicitation" isStim="1" feltEmo="12" feltArsl="6" feltVlnc="4" feltCtrl="3" feltPred="7" cutNr="2" cutLenSec="124.7154" vidRate="60.9708" audRate="48000" audBeginSmp="1229497.5" audEndSmp="7215838.5" vidBeginSmp="1522.5" vidEndSmp="9126.5" mediaFile="73.avi">
    <subject id="24" hasBeard="False" hasMoustache="False" hasGlasses="False"/>
    <track filename="P24-Rec1-2009.09.01.11.59.10_BW1 _BW_Section_2.avi" id="2992.1" type="Video" color="0" view="0" camera="2">
         <annotation filename="P24-Rec1-All-Data-New_Section_2.tsv" id="2992.1.1" type="Gaze" />
         <annotation filename="P24-Rec1-Guide-Cut.tsv" id="2992.1.2" type="GuideCut" />
    </track>
    <track filename="P24-Rec1-2009.09.01.11.59.10_BW2 _BW_Section_2.avi" id="2992.2" type="Video" color="0" view="0" camera="3">
         <annotation filename="P24-Rec1-All-Data-New_Section_2.tsv" id="2992.2.1" type="Gaze" />
         <annotation filename="P24-Rec1-Guide-Cut.tsv" id="2992.2.2" type="GuideCut" />
    </track>
    <track filename="P24-Rec1-2009.09.01.11.59.10_BW3 _BW_Section_2.avi" id="2992.3" type="Video" color="0" view="0" camera="4">
         <annotation filename="P24-Rec1-All-Data-New_Section_2.tsv" id="2992.3.1" type="Gaze" />
         <annotation filename="P24-Rec1-Guide-Cut.tsv" id="2992.3.2" type="GuideCut" />
    </track>
    <track filename="P24-Rec1-2009.09.01.11.59.10_BW4 _BW_Section_2.avi" id="2992.4" type="Video" color="0" view="0" camera="5">
         <annotation filename="P24-Rec1-All-Data-New_Section_2.tsv" id="2992.4.1" type="Gaze" />
         <annotation filename="P24-Rec1-Guide-Cut.tsv" id="2992.4.2" type="GuideCut" />
    </track>
    <track filename="P24-Rec1-2009.09.01.11.59.10_BW5 _BW_Section_2.avi" id="2992.5" type="Video" color="0" view="1" camera="6">
         <annotation filename="P24-Rec1-All-Data-New_Section_2.tsv" id="2992.5.1" type="Gaze" />
         <annotation filename="P24-Rec1-Guide-Cut.tsv" id="2992.5.2" type="GuideCut" />
    </track>
    <track filename="P24-Rec1-2009.09.01.11.59.10_C1 trigger _C_Section_2.avi" id="2992.6" type="Video" color="1" view="0" camera="1">
         <annotation filename="P24-Rec1-All-Data-New_Section_2.tsv" id="2992.6.1" type="Gaze" />
         <annotation filename="P24-Rec1-Guide-Cut.tsv" id="2992.6.2" type="GuideCut" />
    </track>
    <track filename="P24-Rec1-Audio_Section_2.wav" id="2992.7" type="Audio" channel="2">
         <annotation filename="P24-Rec1-Guide-Cut.tsv" id="2992.7.1" type="GuideCut" />
    </track>
    <track filename="Part_24_S_Trial1_emotion.bdf" id="2992.8" type="Physiological">
         <annotation filename="P24-Rec1-All-Data-New_Section_2.tsv" id="2992.8.1" type="Gaze" />
         <annotation filename="P24-Rec1-Guide-Cut.tsv" id="2992.8.2" type="GuideCut" />
    </track>
</session>
